flask_mongoset
