Metadata-Version: 1.1
Name: Flask-MongoSet
Version: 0.1.8
Summary: Access MongoDB from your Flask application
Home-page: https://github.com/Fibio/flask-mongoset
Author: Yehor Nazarkin, Tatyana Kuznetsova
Author-email: nimnull@gmail.com, fibio.tany@gmail.com
License: MIT
Platform: any
Classifier: Development Status :: 4 - Beta
Classifier: Environment :: Web Environment
Classifier: Intended Audience :: Developers
Classifier: License :: OSI Approved :: MIT License
Classifier: Operating System :: OS Independent
Classifier: Programming Language :: Python
Classifier: Topic :: Internet :: WWW/HTTP :: Dynamic Content
Classifier: Topic :: Software Development :: Libraries :: Python Modules
